.DS_Store
pymosarix/__init__.py
pymosarix/pymosarix.py
pymosarix-3.0.dist-info/METADATA
pymosarix-3.0.dist-info/WHEEL
pymosarix-3.0.dist-info/top_level.txt
pymosarix-3.0.dist-info/RECORD
